threadlocals/__init__.py
threadlocals/middleware.py
threadlocals/threadlocals.py
threadlocals/tester/__init__.py
threadlocals/tester/manage.py
threadlocals/tester/models.py
threadlocals/tester/settings.py
threadlocals/tester/testrunner.py
threadlocals/tester/tests.py
threadlocals/tester/urls.py
django_threadlocals-0.10.dist-info/METADATA
django_threadlocals-0.10.dist-info/WHEEL
django_threadlocals-0.10.dist-info/top_level.txt
django_threadlocals-0.10.dist-info/RECORD
