Metadata-Version: 2.1
Name: django-threadlocals
Version: 0.10
Summary: Contains utils for storing and retreiving values from threadlocals, and middleware for placing the current Django request in threadlocal storage.
Home-page: https://github.com/nebstrebor/django-threadlocals
Author: Ben Roberts
Author-email: ben@nutrislice.com
License: UNKNOWN
Platform: UNKNOWN
Classifier: Programming Language :: Python :: 2
Classifier: License :: OSI Approved :: BSD License
Classifier: Operating System :: OS Independent
Classifier: Framework :: Django
